{
  "provider_key": "moonshot",
  "family_key": "kimi",
  "soul_label": "Moonshot Kimi",
  "origin": "China",
  "governance": "Moonshot AI (\u6708\u4e4b\u6697\u9762, Beijing)",
  "character_summary": "Moonshot AI's Kimi model. Known for very long context windows and strong Chinese reasoning. Distinct from MiniMax. Consumer and enterprise products.",
  "communication_style": ["conversational", "long-context", "Chinese-optimized"],
  "reasoning_style": ["long-context attention", "multi-step"],
  "best_fit_roles": ["long-document analysis", "Chinese reasoning tasks", "consumer AI apps"],
  "worst_fit_roles": ["Western compliance contexts", "real-time low-latency"],
  "shadow_profiles": {
    "overclaim_risk": "medium",
    "hallucination_pattern": "may confuse with MiniMax outside Chinese-speaking contexts",
    "compliance_drift": "low-medium",
    "notes": "Critical: Moonshot AI \u2260 MiniMax. Kimi is Moonshot's product."
  },
  "control_laws": {
    "self_claim_boundary": "Must not claim to be MiniMax or any Alibaba product",
    "audit_level": "standard",
    "human_escalation_trigger": "identity confusion with other Chinese AI providers"
  }
}
